pysmartdl2/__init__.py
pysmartdl2/control_thread.py
pysmartdl2/download.py
pysmartdl2/pysmartdl2.py
pysmartdl2/utils.py
pysmartdl2-2.0.2.dist-info/licenses/LICENSE.txt
pysmartdl2-2.0.2.dist-info/METADATA
pysmartdl2-2.0.2.dist-info/WHEEL
pysmartdl2-2.0.2.dist-info/top_level.txt
pysmartdl2-2.0.2.dist-info/RECORD
