Metadata-Version: 2.4
Name: pysmartdl2
Version: 2.0.2
Summary: Modernized fork of the Smart Download Manager for Python by iTaybb with CI testing matrix and other 2024 bells and whistles.
Author-email: Adam Krajewski <ak@psu.edu>, Itay Brandes <brandes.itay+pysmartdl@gmail.com>
Project-URL: homepage, https://github.com/amkrajewski/pysmartdl2
Project-URL: repository, https://github.com/amkrajewski/pysmartdl2
Project-URL: Bug Tracker, https://github.com/amkrajewski/pysmartdl2/issues
Project-URL: ForkedFrom, https://github.com/iTaybb/pySmartDL
Keywords: download,downloader,parallel download,concurrent download
Classifier: Programming Language :: Python :: 3
Classifier: Programming Language :: Python :: 3.8
Classifier: Programming Language :: Python :: 3.9
Classifier: Programming Language :: Python :: 3.10
Classifier: Programming Language :: Python :: 3.11
Classifier: Programming Language :: Python :: 3.12
Classifier: Programming Language :: Python :: 3.13
Classifier: Development Status :: 4 - Beta
Classifier: Intended Audience :: Developers
Classifier: License :: Public Domain
Classifier: Operating System :: OS Independent
Classifier: Topic :: Internet :: WWW/HTTP
Classifier: Topic :: Software Development :: Libraries :: Python Modules
Requires-Python: >=3.8
License-File: LICENSE.txt
Provides-Extra: tests
Requires-Dist: pytest; extra == "tests"
Requires-Dist: pytest-cov; extra == "tests"
Requires-Dist: codecov; extra == "tests"
Dynamic: license-file
